[
  {
    "updated": "2020-02-21 03:30:58.045000+00:00",
    "name": "AC Repair",
    "source": "qubely",
    "source_id": 21484,
    "id": "mJh5ySG24on5VqUMlprz",
    "categories": [
      "Business"
    ]
  },
  {
    "updated": "2020-02-21 03:30:58.608000+00:00",
    "name": "Agency",
    "source": "qubely",
    "source_id": 19646,
    "id": "ODBu76kDETR5E4n37cpH",
    "categories": [
      "Agency"
    ]
  },
  {
    "updated": "2020-02-21 03:30:59.001000+00:00",
    "name": "Asana",
    "source": "qubely",
    "source_id": 60,
    "id": "CYdoUeYy1wGS1O0HYvtd",
    "categories": [
      "Business"
    ]
  },
  {
    "updated": "2020-02-21 03:30:57.793000+00:00",
    "name": "Barber Shop",
    "source": "qubely",
    "source_id": 21517,
    "id": "vAIGGFj5y1ZtlbNH6BmN",
    "categories": [
      "Business"
    ]
  },
  {
    "updated": "2020-02-21 03:30:58.840000+00:00",
    "name": "Business",
    "source": "qubely",
    "source_id": 19631,
    "id": "4mgpK6hv5lJbgEhXugtP",
    "categories": [
      "Business"
    ]
  },
  {
    "updated": "2020-02-21 03:30:58.309000+00:00",
    "name": "Charity",
    "source": "qubely",
    "source_id": 21465,
    "id": "ksUkL3DuQ6980rdLNo55",
    "categories": [
      "Nonprofit"
    ]
  },
  {
    "updated": "2020-02-21 03:30:57.390000+00:00",
    "name": "Coffee Shop",
    "source": "qubely",
    "source_id": 21525,
    "id": "HlHfaRBS7yPTBv6BrR5I",
    "categories": [
      "Restaurant"
    ]
  },
  {
    "updated": "2020-02-21 03:30:58.483000+00:00",
    "name": "Corporate",
    "source": "qubely",
    "source_id": 19686,
    "id": "nKrKWZUJmhnJY6210Ope",
    "categories": [
      "Corporate"
    ]
  },
  {
    "updated": "2020-02-21 03:30:56.577000+00:00",
    "name": "Creative Agency",
    "source": "qubely",
    "source_id": 21728,
    "id": "q8BizzfJ1pUnxNnKaN67",
    "categories": [
      "Agency"
    ]
  },
  {
    "updated": "2020-02-21 03:30:56.992000+00:00",
    "name": "Dentist",
    "source": "qubely",
    "source_id": 21531,
    "id": "9h8lHaKWhTFeNAG6wCy1",
    "categories": [
      "Agency"
    ]
  },
  {
    "updated": "2020-02-21 03:30:55.585000+00:00",
    "name": "Design Agency",
    "source": "qubely",
    "source_id": 22673,
    "id": "uyyQVLD0Oa6pP5WxBdE7",
    "categories": [
      "Agency"
    ]
  },
  {
    "updated": "2020-02-21 03:30:56.002000+00:00",
    "name": "Digital Agency",
    "source": "qubely",
    "source_id": 22409,
    "id": "00wC7hKicdnUYkH5QRXc",
    "categories": [
      "Agency"
    ]
  },
  {
    "updated": "2020-02-21 03:30:56.201000+00:00",
    "name": "Food Truck",
    "source": "qubely",
    "source_id": 22199,
    "id": "a2HJy0KQOKmXq3AkEfvY",
    "categories": [
      "Business",
      "Restaurant"
    ]
  },
  {
    "updated": "2020-02-21 03:30:57.137000+00:00",
    "name": "Furniture",
    "source": "qubely",
    "source_id": 21532,
    "id": "oh7glhYSa13x0iX8tS0z",
    "categories": [
      "Business"
    ]
  },
  {
    "updated": "2020-02-21 03:30:57.950000+00:00",
    "name": "GYM",
    "source": "qubely",
    "source_id": 21503,
    "id": "LcDrsZAx2zwDDMPV0ecO",
    "categories": [
      "Business"
    ]
  },
  {
    "updated": "2020-02-21 03:30:56.867000+00:00",
    "name": "Hand-Craft",
    "source": "qubely",
    "source_id": 21550,
    "id": "PNH120vtgC7VLlUaoWuM",
    "categories": [
      "Business"
    ]
  },
  {
    "updated": "2020-02-21 03:30:56.435000+00:00",
    "name": "Hotel & Resort",
    "source": "qubely",
    "source_id": 21977,
    "id": "c6uD6NjhH6oLA6XNe0gX",
    "categories": [
      "Agency"
    ]
  },
  {
    "updated": "2020-02-21 03:30:55.808000+00:00",
    "name": "Kindergarten",
    "source": "qubely",
    "source_id": 22547,
    "id": "1C3YMjjBgz73jxc4iGRH",
    "categories": [
      "Education"
    ]
  },
  {
    "updated": "2020-02-21 03:30:57.536000+00:00",
    "name": "Restaurant",
    "source": "qubely",
    "source_id": 21489,
    "id": "XjFb4Ipxr44vkcA0lj6N",
    "categories": [
      "Restaurant"
    ]
  }
]